input_interface.v
//TODO: clarify and rename ready signals
// Define module IO
module input_interface (
	// -- input interface
	input clk, input rst_,
	input[7:0] din,
	input[1:0] cmd,
	output ready,
	input engine_done,
	// -- to engine
	output engine_start,
	output[127:0] plain_out,
	output[127:0] key_out
);

// Define FSM states
localparam S_ID = 2'b00;  // Idle state
localparam S_SP = 2'b01;  // Set plaintext state
localparam S_SK = 2'b10;  // Set key state
localparam S_ST = 2'b11;  // Start encryption

// Define registers
// -- FSM state registers
reg[1:0] state, next_state;
initial state=S_ID;
// -- plaintext and key registers
reg[127:0] plain, key;
initial plain = 128'hF00DBABEF00DBABEF00DBABEF00DBABE;
initial key = 128'hF00DBABEF00DBABEF00DBABEF00DBABE;
assign plain_out = plain;
assign key_out = key;
// -- serial input counter registers
reg[3:0] p_i, k_i;
initial p_i=0;
initial k_i=0;
// output engine_start if plain and key ready and start cmd
assign engine_start = (p_i == 4'hF) && (k_i == 4'hF) && (state == S_ST);
// input interface ready if state is idle
assign ready = (state == S_ID);

// Reset functions
task resetkey;
	begin
		key = 128'h00000000000000000000000000000000;
		k_i = 4'h0;
	end
endtask
task resetplain;
	begin
		plain = 128'h00000000000000000000000000000000;
		p_i = 4'h0;
	end
endtask

// Next state combinational logic
always @(negedge clk) state <= next_state;
always @(posedge clk)
begin:next_state_decode
	// reset logic
	if (!rst_) begin
		resetplain();
		resetkey();		
		next_state = S_ID;	
	end
	// command parse
	else case (cmd)
		// Set plaintext state
		S_SP: begin
			// reset if first input
			if (state != S_SP) resetplain();
			else p_i <= p_i+1;
			// return to idle or keep state
			if (p_i == 4'hF) next_state = S_ID; // recieved 16 bytes, return to idle
			else
			begin
				// still reciving bytes
				// read plain from din
				plain = {plain[119:0], din}; // Left shift and insert
				next_state = S_SP;
			end
		end

		// Set key state
		S_SK: begin
			// reset if first input
			if (state != S_SK) resetkey();
			else k_i <= k_i+1;

			// return to idle or keep state
			if (k_i == 4'hF) next_state = S_ID; // recieved 16 bytes, return to idle
			else
			begin
				// still recieving bytes
				// read key from din
				key = {key[119:0], din}; // Left shift and insert
				next_state = S_SK;
			end
		end

		// Start encryption state
		S_ST: begin
			// start engine
			if ((p_i == 4'hF) && (k_i == 4'hF)) next_state = S_ST;
			// return to idle
			if (engine_done) begin
				// encyrption engine is done, we can reset
				p_i = 4'h0;
				k_i = 4'h0;
				resetplain();
				resetkey();
				next_state = S_ID;
			end
			// otherwise wait in this state
			else next_state = S_ST;
		end

		// stay idle
		default: next_state = S_ID;
	endcase
end

`ifndef TOPMODULE
	// the "macro" to dump signals
	initial begin
	$dumpfile ("simulation/input_interface.vcd");
	$dumpvars(0, input_interface);
	end
`endif

endmodule

input_interface_tb.v
`timescale 1ns/1ns // define simulation timescale

// define testbench module for input_interface
module input_interface_tb();

// define tb registers and wires
reg clk_tb = 0;
reg rst_tb = 0;

reg[7:0] din_tb = 0;
reg[1:0] cmd_tb = 0;
reg engind = 0;

wire ready_w;
wire enginC_w;
wire[127:0] plain_tb;
wire[127:0] key_tb;

// define tb->input_interface connections
input_interface i_uut
(
	.clk		(clk_tb),
	.rst_		(rst_tb),
	.din		(din_tb),
	.cmd		(cmd_tb),
	.ready		(ready_w),
	.engine_done	(engind),	// AES engine OK signal return
	.engine_start	(enginC_w),	// AES engine START signal send
	.plain_out	(plain_tb),	// -> AES engine PLAINTEXT
	.key_out	(key_tb)	// -> AES engine KEY
);
// set periodic clock pulse every 1ns
always clk_tb = #1 ~clk_tb;

// state defines
localparam C_ID = 2'b00;  // Idle state
localparam C_SP = 2'b01;  // Set plaintext state
localparam C_SK = 2'b10;  // Set key state
localparam C_ST = 2'b11;  // Start encryption
// Enter this into the command console to add a custom radix for this
// radix define InputCommand {2'b00 "ID" -color blue, 2'b01 "SP" -color yellow, 2'b10 "SK" -color orange, 2'b11 "ST" -color red}
// radix define ReadyBusy {0 "BUSY" -color red, 1 "READY" -color blue, -default symbolic}

// set testing sequence signals
initial begin
	engind = 1; // AES engine done / idle
	
	// reset input interface
	rst_tb = 0;
	#2;
	rst_tb = 1;
	#2;

	// enter plaintext
	cmd_tb = C_SP;
	din_tb = 8'h00;
	#2;
	din_tb = 8'h04;
	#2;
	din_tb = 8'h12;
	#2;
	din_tb = 8'h14;
	#2;
	din_tb = 8'h12;
	#2;
	din_tb = 8'h04;
	#2;
	din_tb = 8'h12;
	#2;
	din_tb = 8'h00;
	#2;
	din_tb = 8'h0C;
	#2;
	din_tb = 8'h00;
	#2;
	din_tb = 8'h13;
	#2;
	din_tb = 8'h11;
	#2;
	din_tb = 8'h08;
	#2;
	din_tb = 8'h23;
	#2;
	din_tb = 8'h19;
	#2;
	din_tb = 8'h19;
	#2;

	// Idle
	cmd_tb = C_ID;
	#2;

	// enter key
	cmd_tb = C_SK;
	din_tb = 8'h24;
	#2;
	din_tb = 8'h75;
	#2;
	din_tb = 8'hA2;
	#2;
	din_tb = 8'hB3;
	#2;
	din_tb = 8'h34;
	#2;
	din_tb = 8'h75;
	#2;
	din_tb = 8'h56;
	#2;
	din_tb = 8'h88;
	#2;
	din_tb = 8'h31;
	#2;
	din_tb = 8'hE2;
	#2;
	din_tb = 8'h12;
	#2;
	din_tb = 8'h00;
	#2;
	din_tb = 8'h13;
	#2;
	din_tb = 8'hAA;
	#2;
	din_tb = 8'h54;
	#2;
	din_tb = 8'h87;
	#2;

	// Idle
	cmd_tb = C_ID;
	#2;

	// Start command
	cmd_tb = C_ST;
	engind = 0; // AES engine not done / busy
	#2;
	#2;
	#2;
	#2;
	#2;
	#2;
	#2;
	#2;
	engind = 1; // Engine done
	#2;

	// Idle
	cmd_tb = C_ID;
	#2;
	$finish;
end

endmodule

simulation/input_interface.vcd
$date
	Thu Mar 14 22:25:20 2024
$end
$version
	Icarus Verilog
$end
$timescale
	1ns
$end
$scope module input_interface_tb $end
$scope module i_uut $end
$var wire 1 ! clk $end
$var wire 2 " cmd [1:0] $end
$var wire 8 # din [7:0] $end
$var wire 1 $ engine_done $end
$var wire 1 % engine_start $end
$var wire 128 & key_out [127:0] $end
$var wire 128 ' plain_out [127:0] $end
$var wire 1 ( rst_ $end
$var wire 1 ) ready $end
$var parameter 2 * S_ID $end
$var parameter 2 + S_SK $end
$var parameter 2 , S_SP $end
$var parameter 2 - S_ST $end
$var reg 4 . k_i [3:0] $end
$var reg 128 / key [127:0] $end
$var reg 2 0 next_state [1:0] $end
$var reg 4 1 p_i [3:0] $end
$var reg 128 2 plain [127:0] $end
$var reg 2 3 state [1:0] $end
$scope begin next_state_decode $end
$upscope $end
$scope task resetkey $end
$upscope $end
$scope task resetplain $end
$upscope $end
$upscope $end
$upscope $end
$enddefinitions $end
$comment Show the parameter values. $end
$dumpall
b11 -
b1 ,
b10 +
b0 *
$end
#0
$dumpvars
bx 3
b11110000000011011011101010111110111100000000110110111010101111101111000000001101101110101011111011110000000011011011101010111110 2
b0 1
bx 0
b11110000000011011011101010111110111100000000110110111010101111101111000000001101101110101011111011110000000011011011101010111110 /
b0 .
x)
0(
b11110000000011011011101010111110111100000000110110111010101111101111000000001101101110101011111011110000000011011011101010111110 '
b11110000000011011011101010111110111100000000110110111010101111101111000000001101101110101011111011110000000011011011101010111110 &
0%
1$
b0 #
b0 "
0!
$end
#1
b0 0
b0 &
b0 /
b0 '
b0 2
1!
#2
1)
b0 3
0!
1(
#3
1!
#4
0!
b1 "
#5
b1 0
1!
#6
0)
b1 3
0!
b100 #
#7
b1 1
b100 '
b100 2
1!
#8
0!
b10010 #
#9
b10 1
b10000010010 '
b10000010010 2
1!
#10
0!
b10100 #
#11
b11 1
b1000001001000010100 '
b1000001001000010100 2
1!
#12
0!
b10010 #
#13
b100 1
b100000100100001010000010010 '
b100000100100001010000010010 2
1!
#14
0!
b100 #
#15
b101 1
b10000010010000101000001001000000100 '
b10000010010000101000001001000000100 2
1!
#16
0!
b10010 #
#17
b110 1
b1000001001000010100000100100000010000010010 '
b1000001001000010100000100100000010000010010 2
1!
#18
0!
b0 #
#19
b111 1
b100000100100001010000010010000001000001001000000000 '
b100000100100001010000010010000001000001001000000000 2
1!
#20
0!
b1100 #
#21
b1000 1
b10000010010000101000001001000000100000100100000000000001100 '
b10000010010000101000001001000000100000100100000000000001100 2
1!
#22
0!
b0 #
#23
b1001 1
b1000001001000010100000100100000010000010010000000000000110000000000 '
b1000001001000010100000100100000010000010010000000000000110000000000 2
1!
#24
0!
b10011 #
#25
b1010 1
b100000100100001010000010010000001000001001000000000000011000000000000010011 '
b100000100100001010000010010000001000001001000000000000011000000000000010011 2
1!
#26
0!
b10001 #
#27
b1011 1
b10000010010000101000001001000000100000100100000000000001100000000000001001100010001 '
b10000010010000101000001001000000100000100100000000000001100000000000001001100010001 2
1!
#28
0!
b1000 #
#29
b1100 1
b1000001001000010100000100100000010000010010000000000000110000000000000100110001000100001000 '
b1000001001000010100000100100000010000010010000000000000110000000000000100110001000100001000 2
1!
#30
0!
b100011 #
#31
b1101 1
b100000100100001010000010010000001000001001000000000000011000000000000010011000100010000100000100011 '
b100000100100001010000010010000001000001001000000000000011000000000000010011000100010000100000100011 2
1!
#32
0!
b11001 #
#33
b1110 1
b10000010010000101000001001000000100000100100000000000001100000000000001001100010001000010000010001100011001 '
b10000010010000101000001001000000100000100100000000000001100000000000001001100010001000010000010001100011001 2
1!
#34
0!
#35
b1111 1
b1000001001000010100000100100000010000010010000000000000110000000000000100110001000100001000001000110001100100011001 '
b1000001001000010100000100100000010000010010000000000000110000000000000100110001000100001000001000110001100100011001 2
1!
#36
0!
b0 "
#37
b0 0
1!
#38
1)
b0 3
0!
b100100 #
b10 "
#39
b10 0
b100100 &
b100100 /
1!
#40
0)
b10 3
0!
b1110101 #
#41
b1 .
b10010001110101 &
b10010001110101 /
1!
#42
0!
b10100010 #
#43
b10 .
b1001000111010110100010 &
b1001000111010110100010 /
1!
#44
0!
b10110011 #
#45
b11 .
b100100011101011010001010110011 &
b100100011101011010001010110011 /
1!
#46
0!
b110100 #
#47
b100 .
b10010001110101101000101011001100110100 &
b10010001110101101000101011001100110100 /
1!
#48
0!
b1110101 #
#49
b101 .
b1001000111010110100010101100110011010001110101 &
b1001000111010110100010101100110011010001110101 /
1!
#50
0!
b1010110 #
#51
b110 .
b100100011101011010001010110011001101000111010101010110 &
b100100011101011010001010110011001101000111010101010110 /
1!
#52
0!
b10001000 #
#53
b111 .
b10010001110101101000101011001100110100011101010101011010001000 &
b10010001110101101000101011001100110100011101010101011010001000 /
1!
#54
0!
b110001 #
#55
b1000 .
b1001000111010110100010101100110011010001110101010101101000100000110001 &
b1001000111010110100010101100110011010001110101010101101000100000110001 /
1!
#56
0!
b11100010 #
#57
b1001 .
b100100011101011010001010110011001101000111010101010110100010000011000111100010 &
b100100011101011010001010110011001101000111010101010110100010000011000111100010 /
1!
#58
0!
b10010 #
#59
b1010 .
b10010001110101101000101011001100110100011101010101011010001000001100011110001000010010 &
b10010001110101101000101011001100110100011101010101011010001000001100011110001000010010 /
1!
#60
0!
b0 #
#61
b1011 .
b1001000111010110100010101100110011010001110101010101101000100000110001111000100001001000000000 &
b1001000111010110100010101100110011010001110101010101101000100000110001111000100001001000000000 /
1!
#62
0!
b10011 #
#63
b1100 .
b100100011101011010001010110011001101000111010101010110100010000011000111100010000100100000000000010011 &
b100100011101011010001010110011001101000111010101010110100010000011000111100010000100100000000000010011 /
1!
#64
0!
b10101010 #
#65
b1101 .
b10010001110101101000101011001100110100011101010101011010001000001100011110001000010010000000000001001110101010 &
b10010001110101101000101011001100110100011101010101011010001000001100011110001000010010000000000001001110101010 /
1!
#66
0!
b1010100 #
#67
b1110 .
b1001000111010110100010101100110011010001110101010101101000100000110001111000100001001000000000000100111010101001010100 &
b1001000111010110100010101100110011010001110101010101101000100000110001111000100001001000000000000100111010101001010100 /
1!
#68
0!
b10000111 #
#69
b1111 .
b100100011101011010001010110011001101000111010101010110100010000011000111100010000100100000000000010011101010100101010010000111 &
b100100011101011010001010110011001101000111010101010110100010000011000111100010000100100000000000010011101010100101010010000111 /
1!
#70
0!
b0 "
#71
b0 0
1!
#72
1)
b0 3
0!
0$
b11 "
#73
b11 0
1!
#74
1%
0)
b11 3
0!
#75
1!
#76
0!
#77
1!
#78
0!
#79
1!
#80
0!
#81
1!
#82
0!
#83
1!
#84
0!
#85
1!
#86
0!
#87
1!
#88
0!
1$
#89
0%
b0 0
b0 &
b0 /
b0 '
b0 2
b0 .
b0 1
1!
#90
1)
b0 3
0!
b0 "
